kincpp/__init__.py
kincpp/kincpp.cpython-310-x86_64-linux-gnu.so
kincpp-0.1.dist-info/METADATA
kincpp-0.1.dist-info/WHEEL
kincpp-0.1.dist-info/top_level.txt
kincpp-0.1.dist-info/RECORD
